nestmodel/ERGM_experiments.py
nestmodel/centralities.py
nestmodel/dict_graph.py
nestmodel/ergm.py
nestmodel/fast_graph.py
nestmodel/fast_rewire.py
nestmodel/fast_rewire2.py
nestmodel/fast_wl.py
nestmodel/load_datasets.py
nestmodel/unified_functions.py
nestmodel/utils.py
nestmodel/wl.py
nestmodel/tests/test_centralities.py
nestmodel/tests/test_fast_graph.py
nestmodel/tests/test_fast_wl.py
nestmodel/tests/test_pagerank.py
nestmodel/tests/test_unified_functions.py
nestmodel/tests/test_utils.py
nestmodel/tests/testing.py
nestmodel/tests/utils_for_test.py
nestmodel-0.1.2.dist-info/METADATA
nestmodel-0.1.2.dist-info/WHEEL
nestmodel-0.1.2.dist-info/top_level.txt
nestmodel-0.1.2.dist-info/RECORD
