Metadata-Version: 2.1
Name: nestmodel
Version: 0.1.2
Summary: This package contains the implementation of the neighborhood structure configuration model for python
Author: Felix Stamm
Author-email: felix.stamm@cssh.rwth-aachen.de
Requires-Python: >=3.8
Requires-Dist: pandas
Requires-Dist: scipy
Requires-Dist: numpy
Requires-Dist: matplotlib
Requires-Dist: numba
Requires-Dist: networkx
Requires-Dist: brokenaxes
Requires-Dist: nbconvert
Requires-Dist: tqdm
